eosapi/__init__.py
eosapi/__version__.py
eosapi/abi.py
eosapi/eosapi.py
eosapi/exceptions.py
eosapi/packer.py
eosapi/proxy.py
eosapi/transaction.py
eosapi_async-2.1.1.dist-info/LICENSE
eosapi_async-2.1.1.dist-info/METADATA
eosapi_async-2.1.1.dist-info/WHEEL
eosapi_async-2.1.1.dist-info/top_level.txt
eosapi_async-2.1.1.dist-info/RECORD
